tensorfit/__init__.py
tensorfit/tensorfit.py
tensorfit/utils.py
tensorfit-0.0.6.dist-info/LICENSE
tensorfit-0.0.6.dist-info/METADATA
tensorfit-0.0.6.dist-info/WHEEL
tensorfit-0.0.6.dist-info/top_level.txt
tensorfit-0.0.6.dist-info/RECORD
