Metadata-Version: 2.1
Name: tensorfit
Version: 0.0.6
Summary: Python package for univariate curve fitting using TensorFlow.
Home-page: https://github.com/dascienz/tensorfit
Author: David Ascienzo
Author-email: dascienz@gmail.com
License: MIT
Keywords: curve,fitting,linear,nonlinear,regression,parametric,machine,learning,tensorflow
Platform: UNKNOWN
Classifier: Programming Language :: Python :: 3
Classifier: License :: OSI Approved :: MIT License
Classifier: Operating System :: OS Independent
Requires-Python: >=3.6
Requires-Dist: numpy
Requires-Dist: tensorflow
